ctyun/__init__.py
ctyun/api.yml
ctyun/inventory.py
ctyun-0.0.12.dist-info/METADATA
ctyun-0.0.12.dist-info/WHEEL
ctyun-0.0.12.dist-info/top_level.txt
ctyun-0.0.12.dist-info/RECORD
