Metadata-Version: 2.1
Name: ctyun
Version: 0.0.12
Summary: Python SDK for China Telecom Cloud(https://www.ctyun.cn)
Home-page: https://github.com/xizhendu/ctyun
Author: Xizhen Du
Author-email: xizhendu@gmail.com
Requires-Dist: PyYAML
Requires-Dist: requests
Requires-Dist: datetime
